{
  "model_id": 509,
  "total_score": 5.8128632614629724e-05,
  "n_valid_comparisons": 2,
  "s_diff": {
    "onnxruntime": 5.635700545976443e-05,
    "torchscript": 0.0
  },
  "delta_opt": {
    "onnxruntime": 1.7716271548652943e-06,
    "torchscript": 0.0
  },
  "crashes": [],
  "crash_info": {},
  "crash_counts": {
    "frontend": 0,
    "backend": 0
  },
  "errors": {},
  "pattern_sequence": [
    [
      "fusion",
      "matmul_bias_relu"
    ],
    [
      "branch",
      "residual_add_relu"
    ],
    [
      "broadcast",
      "sqrt_div_rms"
    ],
    [
      "fusion",
      "matmul_bias_relu"
    ],
    [
      "fusion",
      "matmul_bias_gelu"
    ],
    [
      "constant",
      "redundant_reshape"
    ]
  ],
  "input_shape": [
    1,
    128
  ]
}