{
  "model_id": 266,
  "total_score": 1.854829284501433e-07,
  "n_valid_comparisons": 2,
  "s_diff": {
    "onnxruntime": 1.3038514740765225e-07,
    "torchscript": 0.0
  },
  "delta_opt": {
    "onnxruntime": 5.509778104249106e-08,
    "torchscript": 0.0
  },
  "crashes": [],
  "crash_info": {},
  "crash_counts": {
    "frontend": 0,
    "backend": 0
  },
  "errors": {},
  "pattern_sequence": [
    [
      "normalization",
      "rmsnorm"
    ],
    [
      "layout",
      "gather_reshape"
    ],
    [
      "constant",
      "constant_add_mul"
    ],
    [
      "constant",
      "mul_by_reciprocal"
    ],
    [
      "fusion",
      "matmul_bias_tanh"
    ],
    [
      "normalization",
      "stable_softmax"
    ]
  ],
  "input_shape": [
    1,
    128
  ]
}