{
  "model_id": 84,
  "total_score": 1.873656023585269e-05,
  "n_valid_comparisons": 2,
  "s_diff": {
    "onnxruntime": 9.776473189181688e-06,
    "torchscript": 0.0
  },
  "delta_opt": {
    "onnxruntime": 8.960087046671e-06,
    "torchscript": 0.0
  },
  "crashes": [],
  "crash_info": {},
  "crash_counts": {
    "frontend": 0,
    "backend": 0
  },
  "errors": {},
  "pattern_sequence": [
    [
      "normalization",
      "instance_norm_1d"
    ],
    [
      "constant",
      "where_const_cond"
    ],
    [
      "layout",
      "gather_reshape"
    ],
    [
      "normalization",
      "instance_norm_1d"
    ],
    [
      "normalization",
      "layernorm_dropout_identity"
    ],
    [
      "fusion",
      "matmul_bias_tanh"
    ]
  ],
  "input_shape": [
    1,
    64
  ]
}