{
  "compiler_class": "openvino",
  "affected_compilers": [
    "openvino"
  ],
  "total_score": 0.05906261131167412,
  "input_shape": [
    1,
    16,
    256
  ],
  "pattern_sequence": [
    [
      "layout",
      "squeeze_unsqueeze"
    ],
    [
      "constant",
      "log_exp_cancel"
    ],
    [
      "broadcast",
      "log_clamp"
    ],
    [
      "broadcast",
      "l2_norm"
    ],
    [
      "attention",
      "self_attention_residual"
    ],
    [
      "branch",
      "add_layernorm"
    ]
  ],
  "delta_opt": {
    "openvino": 0.05906261131167412
  },
  "crashes": [],
  "errors": {
    "openvino+opt": "discrepancy rel_diff=0.0591"
  },
  "bug_id": "bug_0201"
}